{
  "title": "District Zero - Episode 1",
  "clips": [
    {
      "shot_id": "SCN_004_SHOT_001",
      "video_url": "null://clips/SCN_004_SHOT_001.mp4",
      "duration_sec": 5,
      "model_used": "null",
      "latency_ms": 0,
      "cost_usd": 0.0,
      "last_frame_url": ""
    },
    {
      "shot_id": "SCN_004_SHOT_002",
      "video_url": "null://clips/SCN_004_SHOT_002.mp4",
      "duration_sec": 5,
      "model_used": "null",
      "latency_ms": 0,
      "cost_usd": 0.0,
      "last_frame_url": ""
    },
    {
      "shot_id": "SCN_004_SHOT_003",
      "video_url": "null://clips/SCN_004_SHOT_003.mp4",
      "duration_sec": 5,
      "model_used": "null",
      "latency_ms": 0,
      "cost_usd": 0.0,
      "last_frame_url": ""
    },
    {
      "shot_id": "SCN_004_SHOT_004",
      "video_url": "null://clips/SCN_004_SHOT_004.mp4",
      "duration_sec": 5,
      "model_used": "null",
      "latency_ms": 0,
      "cost_usd": 0.0,
      "last_frame_url": ""
    },
    {
      "shot_id": "SCN_005_SHOT_001",
      "video_url": "null://clips/SCN_005_SHOT_001.mp4",
      "duration_sec": 6,
      "model_used": "null",
      "latency_ms": 0,
      "cost_usd": 0.0,
      "last_frame_url": ""
    },
    {
      "shot_id": "SCN_005_SHOT_002",
      "video_url": "null://clips/SCN_005_SHOT_002.mp4",
      "duration_sec": 5,
      "model_used": "null",
      "latency_ms": 0,
      "cost_usd": 0.0,
      "last_frame_url": ""
    },
    {
      "shot_id": "SCN_005_SHOT_003",
      "video_url": "null://clips/SCN_005_SHOT_003.mp4",
      "duration_sec": 5,
      "model_used": "null",
      "latency_ms": 0,
      "cost_usd": 0.0,
      "last_frame_url": ""
    },
    {
      "shot_id": "SCN_005_SHOT_004",
      "video_url": "null://clips/SCN_005_SHOT_004.mp4",
      "duration_sec": 4,
      "model_used": "null",
      "latency_ms": 0,
      "cost_usd": 0.0,
      "last_frame_url": ""
    },
    {
      "shot_id": "SCN_006_SHOT_001",
      "video_url": "null://clips/SCN_006_SHOT_001.mp4",
      "duration_sec": 6,
      "model_used": "null",
      "latency_ms": 0,
      "cost_usd": 0.0,
      "last_frame_url": ""
    },
    {
      "shot_id": "SCN_006_SHOT_002",
      "video_url": "null://clips/SCN_006_SHOT_002.mp4",
      "duration_sec": 5,
      "model_used": "null",
      "latency_ms": 0,
      "cost_usd": 0.0,
      "last_frame_url": ""
    },
    {
      "shot_id": "SCN_006_SHOT_003",
      "video_url": "null://clips/SCN_006_SHOT_003.mp4",
      "duration_sec": 5,
      "model_used": "null",
      "latency_ms": 0,
      "cost_usd": 0.0,
      "last_frame_url": ""
    },
    {
      "shot_id": "SCN_006_SHOT_004",
      "video_url": "null://clips/SCN_006_SHOT_004.mp4",
      "duration_sec": 4,
      "model_used": "null",
      "latency_ms": 0,
      "cost_usd": 0.0,
      "last_frame_url": ""
    },
    {
      "shot_id": "SCN_006_SHOT_005",
      "video_url": "null://clips/SCN_006_SHOT_005.mp4",
      "duration_sec": 3,
      "model_used": "null",
      "latency_ms": 0,
      "cost_usd": 0.0,
      "last_frame_url": ""
    },
    {
      "shot_id": "SCN_007_SHOT_001",
      "video_url": "null://clips/SCN_007_SHOT_001.mp4",
      "duration_sec": 6,
      "model_used": "null",
      "latency_ms": 0,
      "cost_usd": 0.0,
      "last_frame_url": ""
    },
    {
      "shot_id": "SCN_007_SHOT_002",
      "video_url": "null://clips/SCN_007_SHOT_002.mp4",
      "duration_sec": 5,
      "model_used": "null",
      "latency_ms": 0,
      "cost_usd": 0.0,
      "last_frame_url": ""
    },
    {
      "shot_id": "SCN_007_SHOT_003",
      "video_url": "null://clips/SCN_007_SHOT_003.mp4",
      "duration_sec": 5,
      "model_used": "null",
      "latency_ms": 0,
      "cost_usd": 0.0,
      "last_frame_url": ""
    },
    {
      "shot_id": "SCN_007_SHOT_004",
      "video_url": "null://clips/SCN_007_SHOT_004.mp4",
      "duration_sec": 5,
      "model_used": "null",
      "latency_ms": 0,
      "cost_usd": 0.0,
      "last_frame_url": ""
    },
    {
      "shot_id": "SCN_008_SHOT_001",
      "video_url": "null://clips/SCN_008_SHOT_001.mp4",
      "duration_sec": 6,
      "model_used": "null",
      "latency_ms": 0,
      "cost_usd": 0.0,
      "last_frame_url": ""
    },
    {
      "shot_id": "SCN_008_SHOT_002",
      "video_url": "null://clips/SCN_008_SHOT_002.mp4",
      "duration_sec": 5,
      "model_used": "null",
      "latency_ms": 0,
      "cost_usd": 0.0,
      "last_frame_url": ""
    },
    {
      "shot_id": "SCN_008_SHOT_003",
      "video_url": "null://clips/SCN_008_SHOT_003.mp4",
      "duration_sec": 5,
      "model_used": "null",
      "latency_ms": 0,
      "cost_usd": 0.0,
      "last_frame_url": ""
    },
    {
      "shot_id": "SCN_008_SHOT_004",
      "video_url": "null://clips/SCN_008_SHOT_004.mp4",
      "duration_sec": 5,
      "model_used": "null",
      "latency_ms": 0,
      "cost_usd": 0.0,
      "last_frame_url": ""
    },
    {
      "shot_id": "SCN_008_SHOT_005",
      "video_url": "null://clips/SCN_008_SHOT_005.mp4",
      "duration_sec": 5,
      "model_used": "null",
      "latency_ms": 0,
      "cost_usd": 0.0,
      "last_frame_url": ""
    },
    {
      "shot_id": "SCN_008_SHOT_006",
      "video_url": "null://clips/SCN_008_SHOT_006.mp4",
      "duration_sec": 5,
      "model_used": "null",
      "latency_ms": 0,
      "cost_usd": 0.0,
      "last_frame_url": ""
    },
    {
      "shot_id": "SCN_009_SHOT_001",
      "video_url": "null://clips/SCN_009_SHOT_001.mp4",
      "duration_sec": 5,
      "model_used": "null",
      "latency_ms": 0,
      "cost_usd": 0.0,
      "last_frame_url": ""
    },
    {
      "shot_id": "SCN_009_SHOT_002",
      "video_url": "null://clips/SCN_009_SHOT_002.mp4",
      "duration_sec": 4,
      "model_used": "null",
      "latency_ms": 0,
      "cost_usd": 0.0,
      "last_frame_url": ""
    },
    {
      "shot_id": "SCN_009_SHOT_003",
      "video_url": "null://clips/SCN_009_SHOT_003.mp4",
      "duration_sec": 5,
      "model_used": "null",
      "latency_ms": 0,
      "cost_usd": 0.0,
      "last_frame_url": ""
    },
    {
      "shot_id": "SCN_009_SHOT_004",
      "video_url": "null://clips/SCN_009_SHOT_004.mp4",
      "duration_sec": 4,
      "model_used": "null",
      "latency_ms": 0,
      "cost_usd": 0.0,
      "last_frame_url": ""
    },
    {
      "shot_id": "SCN_009_SHOT_005",
      "video_url": "null://clips/SCN_009_SHOT_005.mp4",
      "duration_sec": 4,
      "model_used": "null",
      "latency_ms": 0,
      "cost_usd": 0.0,
      "last_frame_url": ""
    },
    {
      "shot_id": "SCN_009_SHOT_006",
      "video_url": "null://clips/SCN_009_SHOT_006.mp4",
      "duration_sec": 5,
      "model_used": "null",
      "latency_ms": 0,
      "cost_usd": 0.0,
      "last_frame_url": ""
    },
    {
      "shot_id": "SCN_010_SHOT_001",
      "video_url": "null://clips/SCN_010_SHOT_001.mp4",
      "duration_sec": 6,
      "model_used": "null",
      "latency_ms": 0,
      "cost_usd": 0.0,
      "last_frame_url": ""
    },
    {
      "shot_id": "SCN_010_SHOT_002",
      "video_url": "null://clips/SCN_010_SHOT_002.mp4",
      "duration_sec": 6,
      "model_used": "null",
      "latency_ms": 0,
      "cost_usd": 0.0,
      "last_frame_url": ""
    },
    {
      "shot_id": "SCN_010_SHOT_003",
      "video_url": "null://clips/SCN_010_SHOT_003.mp4",
      "duration_sec": 6,
      "model_used": "null",
      "latency_ms": 0,
      "cost_usd": 0.0,
      "last_frame_url": ""
    },
    {
      "shot_id": "SCN_010_SHOT_004",
      "video_url": "null://clips/SCN_010_SHOT_004.mp4",
      "duration_sec": 5,
      "model_used": "null",
      "latency_ms": 0,
      "cost_usd": 0.0,
      "last_frame_url": ""
    },
    {
      "shot_id": "SCN_010_SHOT_005",
      "video_url": "null://clips/SCN_010_SHOT_005.mp4",
      "duration_sec": 4,
      "model_used": "null",
      "latency_ms": 0,
      "cost_usd": 0.0,
      "last_frame_url": ""
    },
    {
      "shot_id": "SCN_010_SHOT_006",
      "video_url": "null://clips/SCN_010_SHOT_006.mp4",
      "duration_sec": 6,
      "model_used": "null",
      "latency_ms": 0,
      "cost_usd": 0.0,
      "last_frame_url": ""
    },
    {
      "shot_id": "SCN_010_SHOT_007",
      "video_url": "null://clips/SCN_010_SHOT_007.mp4",
      "duration_sec": 5,
      "model_used": "null",
      "latency_ms": 0,
      "cost_usd": 0.0,
      "last_frame_url": ""
    },
    {
      "shot_id": "SCN_011_SHOT_001",
      "video_url": "null://clips/SCN_011_SHOT_001.mp4",
      "duration_sec": 6,
      "model_used": "null",
      "latency_ms": 0,
      "cost_usd": 0.0,
      "last_frame_url": ""
    },
    {
      "shot_id": "SCN_011_SHOT_002",
      "video_url": "null://clips/SCN_011_SHOT_002.mp4",
      "duration_sec": 6,
      "model_used": "null",
      "latency_ms": 0,
      "cost_usd": 0.0,
      "last_frame_url": ""
    },
    {
      "shot_id": "SCN_011_SHOT_003",
      "video_url": "null://clips/SCN_011_SHOT_003.mp4",
      "duration_sec": 7,
      "model_used": "null",
      "latency_ms": 0,
      "cost_usd": 0.0,
      "last_frame_url": ""
    },
    {
      "shot_id": "SCN_011_SHOT_004",
      "video_url": "null://clips/SCN_011_SHOT_004.mp4",
      "duration_sec": 6,
      "model_used": "null",
      "latency_ms": 0,
      "cost_usd": 0.0,
      "last_frame_url": ""
    },
    {
      "shot_id": "SCN_011_SHOT_005",
      "video_url": "null://clips/SCN_011_SHOT_005.mp4",
      "duration_sec": 5,
      "model_used": "null",
      "latency_ms": 0,
      "cost_usd": 0.0,
      "last_frame_url": ""
    },
    {
      "shot_id": "SCN_011_SHOT_006",
      "video_url": "null://clips/SCN_011_SHOT_006.mp4",
      "duration_sec": 7,
      "model_used": "null",
      "latency_ms": 0,
      "cost_usd": 0.0,
      "last_frame_url": ""
    },
    {
      "shot_id": "SCN_011_SHOT_007",
      "video_url": "null://clips/SCN_011_SHOT_007.mp4",
      "duration_sec": 6,
      "model_used": "null",
      "latency_ms": 0,
      "cost_usd": 0.0,
      "last_frame_url": ""
    },
    {
      "shot_id": "SCN_011_SHOT_008",
      "video_url": "null://clips/SCN_011_SHOT_008.mp4",
      "duration_sec": 5,
      "model_used": "null",
      "latency_ms": 0,
      "cost_usd": 0.0,
      "last_frame_url": ""
    },
    {
      "shot_id": "SCN_011_SHOT_009",
      "video_url": "null://clips/SCN_011_SHOT_009.mp4",
      "duration_sec": 7,
      "model_used": "null",
      "latency_ms": 0,
      "cost_usd": 0.0,
      "last_frame_url": ""
    }
  ],
  "total_shots": 45,
  "generated": 45
}